midi_keyboard/__init__.py
midi_keyboard/__main__.py
midi_keyboard_parametalol-0.0.2.dist-info/METADATA
midi_keyboard_parametalol-0.0.2.dist-info/WHEEL
midi_keyboard_parametalol-0.0.2.dist-info/entry_points.txt
midi_keyboard_parametalol-0.0.2.dist-info/licenses/LICENSE.md
midi_keyboard_parametalol-0.0.2.dist-info/RECORD
