Metadata-Version: 2.4
Name: midi-keyboard-parametalol
Version: 0.0.2
Summary: MIDI to keyboard event mapper
Project-URL: Homepage, https://github.com/parametalol/midi-keyboard
Project-URL: Issues, https://github.com/parametalol/midi-keyboard/issues
Author-email: Michaël Petrov <smartptr@gmail.com>
License: # Custom Restrictive License
License-File: LICENSE.md
Classifier: Operating System :: POSIX :: Linux
Classifier: Programming Language :: Python :: 3
Classifier: Topic :: Multimedia :: Sound/Audio :: MIDI
Requires-Python: <4.0,>=3.4
Requires-Dist: evdev
Requires-Dist: python-rtmidi
